architect_client/__init__.py
architect_client/cli.py
architect_client/libarchitect.py
architect_client-0.8.3.dist-info/DESCRIPTION.rst
architect_client-0.8.3.dist-info/METADATA
architect_client-0.8.3.dist-info/RECORD
architect_client-0.8.3.dist-info/WHEEL
architect_client-0.8.3.dist-info/entry_points.txt
architect_client-0.8.3.dist-info/metadata.json
architect_client-0.8.3.dist-info/top_level.txt
