Metadata-Version: 2.0
Name: architect-client
Version: 0.8.3
Summary: architect-client is a client CLI of Architect, the service modeling, management and visualization platform.
Home-page: https://github.com/cznewt/architect-client/
Author: Aleš Komárek
Author-email: ales.komarek@newt.cz
License: Apache License, Version 2.0
Platform: UNKNOWN
Classifier: Intended Audience :: System Administrators
Classifier: License :: OSI Approved :: Apache Software License
Classifier: Operating System :: POSIX :: Linux
Classifier: Programming Language :: Python
Classifier: Programming Language :: Python :: Implementation :: CPython
Classifier: Programming Language :: Python :: 3
Classifier: Programming Language :: Python :: 3.6
Requires-Dist: pyyaml
Requires-Dist: requests
Requires-Dist: Click
